mobspy/__init__.py
mobspy/_version.py
mobspy/simulation.py
mobspy/variables_and_operators.py
mobspy/data_handler/__init__.py
mobspy/data_handler/process_result_data.py
mobspy/data_handler/time_series_object.py
mobspy/import_manager/__init__.py
mobspy/import_manager/lazy_import_class.py
mobspy/import_manager/profiler_import_time_test.py
mobspy/modules/__init__.py
mobspy/modules/assignments_implementation.py
mobspy/modules/class_of_meta_specie_named_any.py
mobspy/modules/compiler.py
mobspy/modules/context_related_scripts.py
mobspy/modules/event_functions.py
mobspy/modules/function_rate_code.py
mobspy/modules/logic_operator_objects.py
mobspy/modules/meta_class.py
mobspy/modules/meta_class_utils.py
mobspy/modules/mobspy_expressions.py
mobspy/modules/mobspy_parameters.py
mobspy/modules/order_operators.py
mobspy/modules/reaction_construction_nb.py
mobspy/modules/set_counts_module.py
mobspy/modules/species_string_generator.py
mobspy/modules/unit_handler.py
mobspy/modules/user_functions.py
mobspy/parameter_estimation_data_loader/__init__.py
mobspy/parameter_estimation_data_loader/data_loader.py
mobspy/parameter_estimation_data_loader/parameter_estimation_scripts.py
mobspy/parameter_scripts/__init__.py
mobspy/parameter_scripts/parameter_reader.py
mobspy/parameter_scripts/parametric_sweeps.py
mobspy/parameters/__init__.py
mobspy/parameters/default_reader.py
mobspy/parameters/example_reader.py
mobspy/patch_scripts/__init__.py
mobspy/patch_scripts/basico_task_parametrization.py
mobspy/plot_params/__init__.py
mobspy/plot_params/default_plot_reader.py
mobspy/plot_params/example_plot_reader.py
mobspy/plot_scripts/__init__.py
mobspy/plot_scripts/default_plots.py
mobspy/plot_scripts/hierarchical_plot.py
mobspy/plot_scripts/process_plot_data.py
mobspy/plot_scripts/statistics_calculations.py
mobspy/sbml_simulator/SBMLWriter.py
mobspy/sbml_simulator/__init__.py
mobspy/sbml_simulator/builder.py
mobspy/sbml_simulator/run.py
mobspy/simulation_logging/__init__.py
mobspy-2.7.0.dist-info/licenses/LICENSE
mobspy-2.7.0.dist-info/METADATA
mobspy-2.7.0.dist-info/WHEEL
mobspy-2.7.0.dist-info/top_level.txt
mobspy-2.7.0.dist-info/RECORD
