Metadata-Version: 2.4
Name: mobspy
Version: 2.7.0
Summary: A Query-Based Language for Chemical Reaction Networks
Home-page: https://github.com/ROBACON/mobspy
Keywords: CRN,microbiology,synthetic biology,simulation,SBML,specification language
Requires-Python: >=3.11
License-File: LICENSE
Requires-Dist: matplotlib
Requires-Dist: numpy
Requires-Dist: python-copasi<=4.44.295
Requires-Dist: python-libsbml
Requires-Dist: scipy
Requires-Dist: pandas
Requires-Dist: joblib
Requires-Dist: tqdm
Requires-Dist: copasi-basico
Requires-Dist: pint
Provides-Extra: test
Requires-Dist: tellurium; extra == "test"
Dynamic: description
Dynamic: description-content-type
Dynamic: home-page
Dynamic: keywords
Dynamic: license-file
Dynamic: provides-extra
Dynamic: requires-dist
Dynamic: requires-python
Dynamic: summary
